image_processing/__init__.py
image_processing/processing/__init__.py
image_processing/processing/combination.py
image_processing/processing/transformation.py
image_processing/utils/__init__.py
image_processing/utils/io.py
image_processing/utils/pilot.py
image_processing_daniloleone-1.0.4.dist-info/METADATA
image_processing_daniloleone-1.0.4.dist-info/WHEEL
image_processing_daniloleone-1.0.4.dist-info/top_level.txt
image_processing_daniloleone-1.0.4.dist-info/RECORD
