Metadata-Version: 2.1
Name: image-processing_daniloleone
Version: 1.0.4
Summary: Image Processing Package using Skimage
Author: Danilo Leone
Project-URL: Homepage, https://github.com/daniloleonecarneiro/dio-python-image-processing-package
Project-URL: Issues, https://github.com/daniloleonecarneiro/dio-python-image-processing-package/issues
Classifier: Programming Language :: Python :: 3
Classifier: License :: OSI Approved :: MIT License
Classifier: Operating System :: OS Independent
Requires-Python: >=3.8
Requires-Dist: matplotlib
Requires-Dist: nump
Requires-Dist: scikit-image >=0.16.1
